fanolabsasr/__init__.py
fanolabsasr-0.0.1.dist-info/LICENSE
fanolabsasr-0.0.1.dist-info/METADATA
fanolabsasr-0.0.1.dist-info/WHEEL
fanolabsasr-0.0.1.dist-info/top_level.txt
fanolabsasr-0.0.1.dist-info/RECORD
