Metadata-Version: 2.1
Name: fanolabsasr
Version: 0.0.1
Summary: FanoLabs Asr module for Python3
Home-page: https://git.fanoai.cn/SDKs/asr-python
Author: Henry Zheng
Author-email: henry.zheng@fano.ai
License: MIT
Platform: UNKNOWN
Requires-Dist: requests
